README.md
requirements.txt
setup.py
netbox_aws_accounts/.gitignore
netbox_aws_accounts/__init__.py
netbox_aws_accounts/admin.py
netbox_aws_accounts/filters.py
netbox_aws_accounts/forms.py
netbox_aws_accounts/models.py
netbox_aws_accounts/navigation.py
netbox_aws_accounts/tables.py
netbox_aws_accounts/urls.py
netbox_aws_accounts/views.py
netbox_aws_accounts.egg-info/PKG-INFO
netbox_aws_accounts.egg-info/SOURCES.txt
netbox_aws_accounts.egg-info/dependency_links.txt
netbox_aws_accounts.egg-info/requires.txt
netbox_aws_accounts.egg-info/top_level.txt
netbox_aws_accounts/api/serializers.py
netbox_aws_accounts/api/urls.py
netbox_aws_accounts/api/views.py
netbox_aws_accounts/migrations/001_base_initial.py
netbox_aws_accounts/migrations/002_add_vpc_fields.py
netbox_aws_accounts/migrations/__init__.py
netbox_aws_accounts/templates/netbox_aws_accounts/accounts_list.html
netbox_aws_accounts/templates/netbox_aws_accounts/common_edit.html
netbox_aws_accounts/templates/netbox_aws_accounts/common_list.html
netbox_aws_accounts/templates/netbox_aws_accounts/regions_list.html
netbox_aws_accounts/utilities/navigation.py
netbox_aws_accounts/utilities/urls.py
netbox_aws_accounts/utilities/views.py